smurf/__init__.py
smurf/cell_circle.py
smurf/distance.py
smurf/initialParams.py
smurf/lossFunc.py
smurf/model.py
smurf/optimize.py
smurf/utiles.py
smurf/version.py
smurf_imputation-1.0.9.dist-info/LICENSE
smurf_imputation-1.0.9.dist-info/METADATA
smurf_imputation-1.0.9.dist-info/WHEEL
smurf_imputation-1.0.9.dist-info/top_level.txt
smurf_imputation-1.0.9.dist-info/RECORD
