Metadata-Version: 2.1
Name: smurf-imputation
Version: 1.0.9
Summary: SMURF : A matrix factorization method for single-cell
Home-page: https://github.com/deepomicslab/SMURF
Author: Bingchen Wang
Author-email: wangbingchen@buaa.edu.cn
License: UNKNOWN
Platform: UNKNOWN
Classifier: Programming Language :: Python :: 3
Classifier: License :: OSI Approved :: MIT License
Classifier: Operating System :: OS Independent
